discord_oauth2/__init__.py
discord_oauth2/admin.py
discord_oauth2/apps.py
discord_oauth2/models.py
discord_oauth2/urls.py
discord_oauth2/views.py
discord_oauth2/migrations/__init__.py
discord_oauth2/migrations/__pycache__/__init__.cpython-311.pyc
django_discord_oauth2-0.2.0.dist-info/LICENSE
django_discord_oauth2-0.2.0.dist-info/METADATA
django_discord_oauth2-0.2.0.dist-info/WHEEL
django_discord_oauth2-0.2.0.dist-info/entry_points.txt
django_discord_oauth2-0.2.0.dist-info/top_level.txt
django_discord_oauth2-0.2.0.dist-info/RECORD
